bahila_extractor/__init__.py
bahila_extractor/extractor.py
bahila_extractor/theguardian_content.py
bahila_extractor-0.2.8.dist-info/METADATA
bahila_extractor-0.2.8.dist-info/WHEEL
bahila_extractor-0.2.8.dist-info/top_level.txt
bahila_extractor-0.2.8.dist-info/RECORD
