Metadata-Version: 2.1
Name: bahila-extractor
Version: 0.2.8
Summary: UNKNOWN
License: UNKNOWN
Platform: UNKNOWN
Requires-Dist: requests
Requires-Dist: openai
Requires-Dist: bs4
Requires-Dist: langchain
